{"request_id":"6b254d850f254ef792208a76777c275f","status":"success","message":"Построил график по вашему запросу.","selected_view":{"type":"chart","chart_type":"bar","title":"Сравнение по категориям","spec":{"mark":"bar","encoding":{"x":{"field":"category","type":"nominal","title":"Категория"},"y":{"field":"revenue","type":"quantitative","title":"Выручка","aggregate":"sum"}},"data":{"values":[{"category":"Software","revenue":238000},{"category":"Services","revenue":188500},{"category":"Hardware","revenue":126400},{"category":"Training","revenue":64400}]},"title":"Сравнение по категориям"},"normalized_spec":{"mark":"bar","encoding":{"x":{"field":"category","type":"nominal","title":"Категория"},"y":{"field":"revenue","type":"quantitative","title":"Выручка","aggregate":"sum"}},"data":{"values":[{"category":"Software","revenue":238000},{"category":"Services","revenue":188500},{"category":"Hardware","revenue":126400},{"category":"Training","revenue":64400}]},"title":"Сравнение по категориям"},"rendered_artifacts":{"png_uri":null,"svg_uri":null,"html_uri":null}},"artifacts":[{"artifact_id":"6b254d850f254ef792208a76777c275f-table-0756af1c","artifact_type":"table","title":"Таблица результата","uri":"/api/artifacts/6b254d850f254ef792208a76777c275f-table-0756af1c","payload":{"columns":["category","revenue"],"rows":[{"category":"Software","revenue":238000},{"category":"Services","revenue":188500},{"category":"Hardware","revenue":126400},{"category":"Training","revenue":64400}],"row_count":4,"truncated":false,"request_id":"6b254d850f254ef792208a76777c275f"},"metadata":{}},{"artifact_id":"6b254d850f254ef792208a76777c275f-chart_spec-58a89e07","artifact_type":"chart_spec","title":"Сравнение по категориям","uri":"/api/artifacts/6b254d850f254ef792208a76777c275f-chart_spec-58a89e07","payload":{"spec":{"mark":"bar","encoding":{"x":{"field":"category","type":"nominal","title":"Категория"},"y":{"field":"revenue","type":"quantitative","title":"Выручка","aggregate":"sum"}},"data":{"values":[{"category":"Software","revenue":238000},{"category":"Services","revenue":188500},{"category":"Hardware","revenue":126400},{"category":"Training","revenue":64400}]},"title":"Сравнение по категориям"},"request_id":"6b254d850f254ef792208a76777c275f"},"metadata":{}}],"warnings":[],"errors":[],"debug":{"sql_visible":false}}